{  "name": "Extrator Arboreal",  "icon": "thermal:device_tree_extractor",  "category": "thermal:devices",  "read_by_default": true,  "flag": "|mod:thermal_expansion,mod:thermal_cultivation",  "pages": [    {      "type": "text",      "text": "O Arboreal Extractor é um dispositivo que extrai fluido de uma árvore adjacente. Opcionalmente, pode levar fertilizante para aumentar a taxa de produção. farinha de osso aumenta a produção em 1,5x por 8 ciclos, enquanto $(l:thermal:world/plants/phytogro)phyto-gro$(/l) aumenta em 2,0x por 16 ciclos. Árvores diferentes produzem fluidos diferentes; use JEI para ver as receitas disponíveis."    },    {      "type": "crafting",      "recipe": "thermal:device_tree_extractor",      "title": "Extrator Arboreal"    },    {      "type": "text",      "title": "Compatibilidade de Aprimoramento",      "text": "$(li)$(l:thermal:technology/augments/integral_components)Componentes Integrais$(/l)$(li)$(l:thermal:technology/augments/fluid_tank)Construção de Tanque Expandido$(/l)"    }  ]}