{
  "name": "通量電鑽",
  "icon": "thermal:flux_drill",
  "category": "thermal:tools",
  "read_by_default": true,
  "flag": "mod:thermal_innovation",
  "pages": [
    {
      "type": "patchouli:text",
      "text": "使用紅石通量有效地挖掘石頭和泥土類型的方塊。它可以在匠魂的工作台中充能和增強。挖掘黑曜石需要強化或更高的整合組件。安裝徑向範圍拓展後，按 \"$(k:cofh.mode_change_increment)\" 可在挖掘半徑之間切換。它可以被附魔$(l:thermal:world/holding)擴容$(/l)以提高紅石通量容量。"
    },
    {
      "type": "thermal:double_crafting_page",
      "A.recipe": "thermal:drill_head",
      "B.recipe": "thermal:flux_drill"
    },
    {
      "type": "patchouli:text",
      "title": "增強相容性",
      "text": "$(li)$(l:thermal:technology/augments/integral_components)整合組件$(/l)$(li)$(l:thermal:technology/augments/rf_coil)擴展通量線圈$(/l)$(li)$(l:thermal:technology/augments/rf_coil_storage)穩態通量線圈$(/l)$(li)$(l:thermal:technology/augments/rf_coil_xfer)強導通量線圈$(/l)$(li)$(l:thermal:technology/augments/area_radius)徑向範圍拓展$(/l)"
    }
  ]
}